README.rst
setup.cfg
setup.py
./__init__.py
./product.py
./product.xml
./storage_area.py
./storage_area.xml
./tryton.cfg
./tests/__init__.py
./tests/test_views_depends.py
./view/product_form.xml
./view/product_storage_area_form.xml
./view/product_storage_area_tree.xml
./view/storage_area_form.xml
./view/storage_area_tree.xml
openlabs_product_storage_area.egg-info/PKG-INFO
openlabs_product_storage_area.egg-info/SOURCES.txt
openlabs_product_storage_area.egg-info/dependency_links.txt
openlabs_product_storage_area.egg-info/entry_points.txt
openlabs_product_storage_area.egg-info/not-zip-safe
openlabs_product_storage_area.egg-info/requires.txt
openlabs_product_storage_area.egg-info/top_level.txt